{"class_map": {"valid": [{"class": "box", "map@50:95": 0.9125074457317728, "map@50": 1.0, "precision": 1.0, "recall": 1.0, "f1_score": 1.0}, {"class": "phone_back", "map@50:95": 0.9867423327698625, "map@50": 1.0, "precision": 1.0, "recall": 1.0, "f1_score": 1.0}, {"class": "phone_front", "map@50:95": 0.997428636961876, "map@50": 1.0, "precision": 1.0, "recall": 1.0, "f1_score": 1.0}, {"class": "all", "map@50:95": 0.9655594718211704, "map@50": 1.0, "precision": 1.0, "recall": 1.0, "f1_score": 1.0}], "test": [{"class": "box", "map@50:95": 0.9617114568599721, "map@50": 0.9881188118811886, "precision": 0.9, "recall": 1.0, "f1_score": 0.9473684210526316}, {"class": "phone_back", "map@50:95": 0.9693069306930694, "map@50": 1.0, "precision": 1.0, "recall": 1.0, "f1_score": 1.0}, {"class": "phone_front", "map@50:95": 1.0, "map@50": 1.0, "precision": 1.0, "recall": 1.0, "f1_score": 1.0}, {"class": "all", "map@50:95": 0.9770061291843469, "map@50": 0.996039603960396, "precision": 0.9666666666666667, "recall": 1.0, "f1_score": 0.9824561403508772}]}, "map": 1.0, "precision": 1.0, "recall": 1.0, "f1_score": 1.0}